{
  "schema_version": "1.0",
  "generated_at": "2026-07-22T17:01:45.226184Z",
  "source": {
    "page_url": "https://en.wikipedia.org/wiki/Opinion_polling_for_the_2027_French_presidential_election",
    "revision_id": "1363698303",
    "license": "CC BY-SA 4.0",
    "modified": true,
    "attribution": "Derived from Wikipedia contributors"
  },
  "events": [
    {
      "event_id": "02eb93085dba2928e03e009a2979f3545e59f44de55058f6bace66bd31b6e9ba",
      "round": "second_round",
      "pollster": "Harris Interactive",
      "commissioner": null,
      "publication_date": null,
      "fieldwork_start": "2026-07-07",
      "fieldwork_end": "2026-07-08",
      "sample_size": 1582,
      "matchup_key": "2b8ffef90d7e509dde822706d04e47374f6afb95cbdddc43ba28aa7f81497cfc",
      "hypothesis": "Second round — Jean-Luc Mélenchon vs Marine Le Pen",
      "candidates": [
        {
          "name": "Jean-Luc Mélenchon",
          "score": 33
        },
        {
          "name": "Marine Le Pen",
          "score": 67
        }
      ],
      "margin": 34,
      "source_url": "https://www.rtl.fr/actu/politique/sondage-rtl-presidentielle-2027-marine-le-pen-progresse-dans-les-intentions-de-vote-apres-l-annonce-de-sa-candidature-7900653723",
      "source_page_url": "https://en.wikipedia.org/wiki/Opinion_polling_for_the_2027_French_presidential_election",
      "source_section": "Mélenchon vs. Le Pen",
      "source_section_path": [
        "Second round",
        "Mélenchon vs. Le Pen"
      ],
      "source_scope": "current_tested",
      "quality_flags": []
    },
    {
      "event_id": "51ee54b37563986dda665e60e02cbec6506eb9b56026e7b06334946a2bf1c4da",
      "round": "second_round",
      "pollster": "Harris Interactive",
      "commissioner": null,
      "publication_date": null,
      "fieldwork_start": "2026-07-07",
      "fieldwork_end": "2026-07-08",
      "sample_size": 1582,
      "matchup_key": "783f1f9054fbd7487dab0b1689b7c3f1af200ebfec1ecf75d0078c6e65833198",
      "hypothesis": "Second round — Édouard Philippe vs Marine Le Pen",
      "candidates": [
        {
          "name": "Édouard Philippe",
          "score": 49
        },
        {
          "name": "Marine Le Pen",
          "score": 51
        }
      ],
      "margin": 2,
      "source_url": "https://www.rtl.fr/actu/politique/sondage-rtl-presidentielle-2027-marine-le-pen-progresse-dans-les-intentions-de-vote-apres-l-annonce-de-sa-candidature-7900653723",
      "source_page_url": "https://en.wikipedia.org/wiki/Opinion_polling_for_the_2027_French_presidential_election",
      "source_section": "Philippe vs. Le Pen",
      "source_section_path": [
        "Second round",
        "Philippe vs. Le Pen"
      ],
      "source_scope": "current_tested",
      "quality_flags": []
    },
    {
      "event_id": "1e71819225ee25767190571173662b08ec5ade5c3590345c4b04107033c6f67b",
      "round": "second_round",
      "pollster": "Harris Interactive",
      "commissioner": null,
      "publication_date": null,
      "fieldwork_start": "2026-07-07",
      "fieldwork_end": "2026-07-08",
      "sample_size": 1582,
      "matchup_key": "b02eec6f80ed4da2173d14e7ed6b2aa3877cf725f91d41f2c8850c66af2640ed",
      "hypothesis": "Second round — Gabriel Attal vs Marine Le Pen",
      "candidates": [
        {
          "name": "Gabriel Attal",
          "score": 45
        },
        {
          "name": "Marine Le Pen",
          "score": 55
        }
      ],
      "margin": 10,
      "source_url": "https://www.rtl.fr/actu/politique/sondage-rtl-presidentielle-2027-marine-le-pen-progresse-dans-les-intentions-de-vote-apres-l-annonce-de-sa-candidature-7900653723",
      "source_page_url": "https://en.wikipedia.org/wiki/Opinion_polling_for_the_2027_French_presidential_election",
      "source_section": "Attal vs. Le Pen",
      "source_section_path": [
        "Second round",
        "Attal vs. Le Pen"
      ],
      "source_scope": "current_tested",
      "quality_flags": []
    },
    {
      "event_id": "86d6747c4a8d78d7900c8fbc826ca62816f2c3760bd801e22a969edf8edaa940",
      "round": "second_round",
      "pollster": "Ifop",
      "commissioner": null,
      "publication_date": null,
      "fieldwork_start": "2026-07-07",
      "fieldwork_end": "2026-07-08",
      "sample_size": 984,
      "matchup_key": "2b8ffef90d7e509dde822706d04e47374f6afb95cbdddc43ba28aa7f81497cfc",
      "hypothesis": "Second round — Jean-Luc Mélenchon vs Marine Le Pen",
      "candidates": [
        {
          "name": "Jean-Luc Mélenchon",
          "score": 30
        },
        {
          "name": "Marine Le Pen",
          "score": 70
        }
      ],
      "margin": 40,
      "source_url": "https://www.ifop.com/wp-content/uploads/2026/07/122649-resultats.pdf",
      "source_page_url": "https://en.wikipedia.org/wiki/Opinion_polling_for_the_2027_French_presidential_election",
      "source_section": "Mélenchon vs. Le Pen",
      "source_section_path": [
        "Second round",
        "Mélenchon vs. Le Pen"
      ],
      "source_scope": "current_tested",
      "quality_flags": []
    },
    {
      "event_id": "fddd7528b269fdaa2b56b74c9b670e7abcffd9b69dbdcf14103fa05ea3496e1d",
      "round": "second_round",
      "pollster": "Ifop",
      "commissioner": null,
      "publication_date": null,
      "fieldwork_start": "2026-07-07",
      "fieldwork_end": "2026-07-08",
      "sample_size": 984,
      "matchup_key": "783f1f9054fbd7487dab0b1689b7c3f1af200ebfec1ecf75d0078c6e65833198",
      "hypothesis": "Second round — Édouard Philippe vs Marine Le Pen",
      "candidates": [
        {
          "name": "Édouard Philippe",
          "score": 46
        },
        {
          "name": "Marine Le Pen",
          "score": 54
        }
      ],
      "margin": 8,
      "source_url": "https://www.ifop.com/wp-content/uploads/2026/07/122649-resultats.pdf",
      "source_page_url": "https://en.wikipedia.org/wiki/Opinion_polling_for_the_2027_French_presidential_election",
      "source_section": "Philippe vs. Le Pen",
      "source_section_path": [
        "Second round",
        "Philippe vs. Le Pen"
      ],
      "source_scope": "current_tested",
      "quality_flags": []
    },
    {
      "event_id": "4329562433e1d453994aaf6f740c4b7c9566ea944139e6da1e70cf4fb7d2409c",
      "round": "second_round",
      "pollster": "Ifop",
      "commissioner": null,
      "publication_date": null,
      "fieldwork_start": "2026-07-07",
      "fieldwork_end": "2026-07-08",
      "sample_size": 984,
      "matchup_key": "b02eec6f80ed4da2173d14e7ed6b2aa3877cf725f91d41f2c8850c66af2640ed",
      "hypothesis": "Second round — Gabriel Attal vs Marine Le Pen",
      "candidates": [
        {
          "name": "Gabriel Attal",
          "score": 45
        },
        {
          "name": "Marine Le Pen",
          "score": 55
        }
      ],
      "margin": 10,
      "source_url": "https://www.ifop.com/wp-content/uploads/2026/07/122649-resultats.pdf",
      "source_page_url": "https://en.wikipedia.org/wiki/Opinion_polling_for_the_2027_French_presidential_election",
      "source_section": "Attal vs. Le Pen",
      "source_section_path": [
        "Second round",
        "Attal vs. Le Pen"
      ],
      "source_scope": "current_tested",
      "quality_flags": []
    },
    {
      "event_id": "44e40a299a99abc4491ed1516b60aaf91367a8e87cb5b6f4f6cb4c771e15ea36",
      "round": "second_round",
      "pollster": "Harris Interactive",
      "commissioner": null,
      "publication_date": null,
      "fieldwork_start": "2026-05-25",
      "fieldwork_end": "2026-05-27",
      "sample_size": 1744,
      "matchup_key": "2b8ffef90d7e509dde822706d04e47374f6afb95cbdddc43ba28aa7f81497cfc",
      "hypothesis": "Second round — Jean-Luc Mélenchon vs Marine Le Pen",
      "candidates": [
        {
          "name": "Jean-Luc Mélenchon",
          "score": 33
        },
        {
          "name": "Marine Le Pen",
          "score": 67
        }
      ],
      "margin": 34,
      "source_url": "https://tolunacorporate.com/wp-content/uploads/2026/05/Rapport-Toluna-Barometre-Presidentielle-2027-Vague-2-M6-RTL-Mai-2026.pdf",
      "source_page_url": "https://en.wikipedia.org/wiki/Opinion_polling_for_the_2027_French_presidential_election",
      "source_section": "Mélenchon vs. Le Pen",
      "source_section_path": [
        "Second round",
        "Mélenchon vs. Le Pen"
      ],
      "source_scope": "current_tested",
      "quality_flags": []
    },
    {
      "event_id": "638052d5ce2863436e1f9eddd993107aaef67523126870b5a093c2fb4f24ede6",
      "round": "second_round",
      "pollster": "Harris Interactive",
      "commissioner": null,
      "publication_date": null,
      "fieldwork_start": "2026-05-25",
      "fieldwork_end": "2026-05-27",
      "sample_size": 1744,
      "matchup_key": "65030a6fcb5d4727884092ec44ff4f0a4d1375109b1cea022a76f117a403880b",
      "hypothesis": "Second round — Édouard Philippe vs Jordan Bardella",
      "candidates": [
        {
          "name": "Édouard Philippe",
          "score": 46
        },
        {
          "name": "Jordan Bardella",
          "score": 54
        }
      ],
      "margin": 8,
      "source_url": "https://tolunacorporate.com/wp-content/uploads/2026/05/Rapport-Toluna-Barometre-Presidentielle-2027-Vague-2-M6-RTL-Mai-2026.pdf",
      "source_page_url": "https://en.wikipedia.org/wiki/Opinion_polling_for_the_2027_French_presidential_election",
      "source_section": "Philippe vs. Bardella",
      "source_section_path": [
        "Second round",
        "Declined to be candidates",
        "Philippe vs. Bardella"
      ],
      "source_scope": "source_declined_candidate_section",
      "quality_flags": []
    },
    {
      "event_id": "c18700e0a4bd23b93c1df0ab5bdee04af73455ae5392e6b3b917af0f7cd98f3c",
      "round": "second_round",
      "pollster": "Harris Interactive",
      "commissioner": null,
      "publication_date": null,
      "fieldwork_start": "2026-05-25",
      "fieldwork_end": "2026-05-27",
      "sample_size": 1744,
      "matchup_key": "783f1f9054fbd7487dab0b1689b7c3f1af200ebfec1ecf75d0078c6e65833198",
      "hypothesis": "Second round — Édouard Philippe vs Marine Le Pen",
      "candidates": [
        {
          "name": "Édouard Philippe",
          "score": 48
        },
        {
          "name": "Marine Le Pen",
          "score": 52
        }
      ],
      "margin": 4,
      "source_url": "https://tolunacorporate.com/wp-content/uploads/2026/05/Rapport-Toluna-Barometre-Presidentielle-2027-Vague-2-M6-RTL-Mai-2026.pdf",
      "source_page_url": "https://en.wikipedia.org/wiki/Opinion_polling_for_the_2027_French_presidential_election",
      "source_section": "Philippe vs. Le Pen",
      "source_section_path": [
        "Second round",
        "Philippe vs. Le Pen"
      ],
      "source_scope": "current_tested",
      "quality_flags": []
    },
    {
      "event_id": "6a8e80c4ee8dd9df86d05a6d400eb08404c9a358459606e5f58d281c53a3cec1",
      "round": "second_round",
      "pollster": "Harris Interactive",
      "commissioner": null,
      "publication_date": null,
      "fieldwork_start": "2026-05-25",
      "fieldwork_end": "2026-05-27",
      "sample_size": 1744,
      "matchup_key": "b02eec6f80ed4da2173d14e7ed6b2aa3877cf725f91d41f2c8850c66af2640ed",
      "hypothesis": "Second round — Gabriel Attal vs Marine Le Pen",
      "candidates": [
        {
          "name": "Gabriel Attal",
          "score": 46
        },
        {
          "name": "Marine Le Pen",
          "score": 54
        }
      ],
      "margin": 8,
      "source_url": "https://tolunacorporate.com/wp-content/uploads/2026/05/Rapport-Toluna-Barometre-Presidentielle-2027-Vague-2-M6-RTL-Mai-2026.pdf",
      "source_page_url": "https://en.wikipedia.org/wiki/Opinion_polling_for_the_2027_French_presidential_election",
      "source_section": "Attal vs. Le Pen",
      "source_section_path": [
        "Second round",
        "Attal vs. Le Pen"
      ],
      "source_scope": "current_tested",
      "quality_flags": []
    },
    {
      "event_id": "072422ff943508c4d11efe3aad53a6ce2509894ded4344d5f60092a05e701762",
      "round": "second_round",
      "pollster": "Harris Interactive",
      "commissioner": null,
      "publication_date": null,
      "fieldwork_start": "2026-05-25",
      "fieldwork_end": "2026-05-27",
      "sample_size": 1744,
      "matchup_key": "c8d3b8b02c325c5cf8da01e329f0eab1202473e2754696709fbbde861dce2b06",
      "hypothesis": "Second round — Jean-Luc Mélenchon vs Jordan Bardella",
      "candidates": [
        {
          "name": "Jean-Luc Mélenchon",
          "score": 32
        },
        {
          "name": "Jordan Bardella",
          "score": 68
        }
      ],
      "margin": 36,
      "source_url": "https://tolunacorporate.com/wp-content/uploads/2026/05/Rapport-Toluna-Barometre-Presidentielle-2027-Vague-2-M6-RTL-Mai-2026.pdf",
      "source_page_url": "https://en.wikipedia.org/wiki/Opinion_polling_for_the_2027_French_presidential_election",
      "source_section": "Mélenchon vs. Bardella",
      "source_section_path": [
        "Second round",
        "Declined to be candidates",
        "Mélenchon vs. Bardella"
      ],
      "source_scope": "source_declined_candidate_section",
      "quality_flags": []
    },
    {
      "event_id": "7fdc2d5d10b2a975e7edacb9d21d1fc10a7de8d86c322597432a6c9507a64f72",
      "round": "second_round",
      "pollster": "Harris Interactive",
      "commissioner": null,
      "publication_date": null,
      "fieldwork_start": "2026-05-25",
      "fieldwork_end": "2026-05-27",
      "sample_size": 1744,
      "matchup_key": "e4174856272b72a0a855e88664f106fa90827e450b1692e3fdb78a0d2b03a683",
      "hypothesis": "Second round — Gabriel Attal vs Jordan Bardella",
      "candidates": [
        {
          "name": "Gabriel Attal",
          "score": 43
        },
        {
          "name": "Jordan Bardella",
          "score": 57
        }
      ],
      "margin": 14,
      "source_url": "https://tolunacorporate.com/wp-content/uploads/2026/05/Rapport-Toluna-Barometre-Presidentielle-2027-Vague-2-M6-RTL-Mai-2026.pdf",
      "source_page_url": "https://en.wikipedia.org/wiki/Opinion_polling_for_the_2027_French_presidential_election",
      "source_section": "Attal vs. Bardella",
      "source_section_path": [
        "Second round",
        "Declined to be candidates",
        "Attal vs. Bardella"
      ],
      "source_scope": "source_declined_candidate_section",
      "quality_flags": []
    },
    {
      "event_id": "ad3a0b93116e124eb3f8f5149fdef9599016af6a1d89b3aaff20886ba488a6e8",
      "round": "second_round",
      "pollster": "Odoxa",
      "commissioner": null,
      "publication_date": null,
      "fieldwork_start": "2026-05-20",
      "fieldwork_end": "2026-05-21",
      "sample_size": 1005,
      "matchup_key": "65030a6fcb5d4727884092ec44ff4f0a4d1375109b1cea022a76f117a403880b",
      "hypothesis": "Second round — Édouard Philippe vs Jordan Bardella",
      "candidates": [
        {
          "name": "Édouard Philippe",
          "score": 48
        },
        {
          "name": "Jordan Bardella",
          "score": 52
        }
      ],
      "margin": 4,
      "source_url": "https://www.odoxa.fr/sondage/philippe-seffondre-melenchon-decolle-bardella-simpose/",
      "source_page_url": "https://en.wikipedia.org/wiki/Opinion_polling_for_the_2027_French_presidential_election",
      "source_section": "Philippe vs. Bardella",
      "source_section_path": [
        "Second round",
        "Declined to be candidates",
        "Philippe vs. Bardella"
      ],
      "source_scope": "source_declined_candidate_section",
      "quality_flags": []
    },
    {
      "event_id": "0473f1e402b73add342ffa3029f3c4c9c2b24935284a5a917763c72479853b5f",
      "round": "second_round",
      "pollster": "Elabe",
      "commissioner": null,
      "publication_date": null,
      "fieldwork_start": "2026-03-25",
      "fieldwork_end": "2026-03-27",
      "sample_size": 1504,
      "matchup_key": "65030a6fcb5d4727884092ec44ff4f0a4d1375109b1cea022a76f117a403880b",
      "hypothesis": "Second round — Édouard Philippe vs Jordan Bardella",
      "candidates": [
        {
          "name": "Édouard Philippe",
          "score": 51.5
        },
        {
          "name": "Jordan Bardella",
          "score": 48.5
        }
      ],
      "margin": 3,
      "source_url": "https://elabe.fr/fichier-pdf/12955-20260328_elabe_bfmtv_la-tribune-dimanche_election-presidentielle-2027/",
      "source_page_url": "https://en.wikipedia.org/wiki/Opinion_polling_for_the_2027_French_presidential_election",
      "source_section": "Philippe vs. Bardella",
      "source_section_path": [
        "Second round",
        "Declined to be candidates",
        "Philippe vs. Bardella"
      ],
      "source_scope": "source_declined_candidate_section",
      "quality_flags": []
    },
    {
      "event_id": "36dd5bbadfe46c61673a5f947452562b8986666bb0c779f53a253556aba7c489",
      "round": "second_round",
      "pollster": "Elabe",
      "commissioner": null,
      "publication_date": null,
      "fieldwork_start": "2026-03-25",
      "fieldwork_end": "2026-03-27",
      "sample_size": 1504,
      "matchup_key": "783f1f9054fbd7487dab0b1689b7c3f1af200ebfec1ecf75d0078c6e65833198",
      "hypothesis": "Second round — Édouard Philippe vs Marine Le Pen",
      "candidates": [
        {
          "name": "Édouard Philippe",
          "score": 53
        },
        {
          "name": "Marine Le Pen",
          "score": 47
        }
      ],
      "margin": 6,
      "source_url": "https://elabe.fr/fichier-pdf/12955-20260328_elabe_bfmtv_la-tribune-dimanche_election-presidentielle-2027/",
      "source_page_url": "https://en.wikipedia.org/wiki/Opinion_polling_for_the_2027_French_presidential_election",
      "source_section": "Philippe vs. Le Pen",
      "source_section_path": [
        "Second round",
        "Philippe vs. Le Pen"
      ],
      "source_scope": "current_tested",
      "quality_flags": []
    },
    {
      "event_id": "7f6ae930b92f8f1dbfda4fcee1356fbd96a0c8e551afff1ba8b9c71b2adef804",
      "round": "second_round",
      "pollster": "Elabe",
      "commissioner": null,
      "publication_date": null,
      "fieldwork_start": "2026-03-25",
      "fieldwork_end": "2026-03-27",
      "sample_size": 1504,
      "matchup_key": "9fe645f9f24c1f7dc42b5a70cdc1b3fd829cbfeefcf3b38b82593419ad63daab",
      "hypothesis": "Second round — Bruno Retailleau vs Jordan Bardella",
      "candidates": [
        {
          "name": "Bruno Retailleau",
          "score": 42
        },
        {
          "name": "Jordan Bardella",
          "score": 58
        }
      ],
      "margin": 16,
      "source_url": "https://elabe.fr/fichier-pdf/12955-20260328_elabe_bfmtv_la-tribune-dimanche_election-presidentielle-2027/",
      "source_page_url": "https://en.wikipedia.org/wiki/Opinion_polling_for_the_2027_French_presidential_election",
      "source_section": "Retailleau vs. Bardella",
      "source_section_path": [
        "Second round",
        "Declined to be candidates",
        "Retailleau vs. Bardella"
      ],
      "source_scope": "source_declined_candidate_section",
      "quality_flags": []
    },
    {
      "event_id": "63b495f994f40cb0cde79780357853041487e0e689a8df690fe93bf0564f90f2",
      "round": "second_round",
      "pollster": "Elabe",
      "commissioner": null,
      "publication_date": null,
      "fieldwork_start": "2026-03-25",
      "fieldwork_end": "2026-03-27",
      "sample_size": 1504,
      "matchup_key": "b02eec6f80ed4da2173d14e7ed6b2aa3877cf725f91d41f2c8850c66af2640ed",
      "hypothesis": "Second round — Gabriel Attal vs Marine Le Pen",
      "candidates": [
        {
          "name": "Gabriel Attal",
          "score": 49
        },
        {
          "name": "Marine Le Pen",
          "score": 51
        }
      ],
      "margin": 2,
      "source_url": "https://elabe.fr/fichier-pdf/12955-20260328_elabe_bfmtv_la-tribune-dimanche_election-presidentielle-2027/",
      "source_page_url": "https://en.wikipedia.org/wiki/Opinion_polling_for_the_2027_French_presidential_election",
      "source_section": "Attal vs. Le Pen",
      "source_section_path": [
        "Second round",
        "Attal vs. Le Pen"
      ],
      "source_scope": "current_tested",
      "quality_flags": []
    },
    {
      "event_id": "27e4454068e9180078cf1d425d5775e68d137d79c876c0169d6b0bb43dd9078b",
      "round": "second_round",
      "pollster": "Elabe",
      "commissioner": null,
      "publication_date": null,
      "fieldwork_start": "2026-03-25",
      "fieldwork_end": "2026-03-27",
      "sample_size": 1504,
      "matchup_key": "c8d3b8b02c325c5cf8da01e329f0eab1202473e2754696709fbbde861dce2b06",
      "hypothesis": "Second round — Jean-Luc Mélenchon vs Jordan Bardella",
      "candidates": [
        {
          "name": "Jean-Luc Mélenchon",
          "score": 28.5
        },
        {
          "name": "Jordan Bardella",
          "score": 71.5
        }
      ],
      "margin": 43,
      "source_url": "https://elabe.fr/fichier-pdf/12955-20260328_elabe_bfmtv_la-tribune-dimanche_election-presidentielle-2027/",
      "source_page_url": "https://en.wikipedia.org/wiki/Opinion_polling_for_the_2027_French_presidential_election",
      "source_section": "Mélenchon vs. Bardella",
      "source_section_path": [
        "Second round",
        "Declined to be candidates",
        "Mélenchon vs. Bardella"
      ],
      "source_scope": "source_declined_candidate_section",
      "quality_flags": []
    },
    {
      "event_id": "3b376a11e17e23508c0f74a305445ca68b134576e6aa5d417e205011d66573f9",
      "round": "second_round",
      "pollster": "Elabe",
      "commissioner": null,
      "publication_date": null,
      "fieldwork_start": "2026-03-25",
      "fieldwork_end": "2026-03-27",
      "sample_size": 1504,
      "matchup_key": "f73fc321237dfe37284e53ff09259b95fd94d775515ac7edd64d296900e943ad",
      "hypothesis": "Second round — Raphaël Glucksmann vs Jordan Bardella",
      "candidates": [
        {
          "name": "Raphaël Glucksmann",
          "score": 41.5
        },
        {
          "name": "Jordan Bardella",
          "score": 58.5
        }
      ],
      "margin": 17,
      "source_url": "https://elabe.fr/fichier-pdf/12955-20260328_elabe_bfmtv_la-tribune-dimanche_election-presidentielle-2027/",
      "source_page_url": "https://en.wikipedia.org/wiki/Opinion_polling_for_the_2027_French_presidential_election",
      "source_section": "Glucksmann vs. Bardella",
      "source_section_path": [
        "Second round",
        "Declined to be candidates",
        "Glucksmann vs. Bardella"
      ],
      "source_scope": "source_declined_candidate_section",
      "quality_flags": []
    },
    {
      "event_id": "f7a3b8a301038c0e4233e412894d9c43e1ebf44e9a68243a145cdc2b8f4c3436",
      "round": "second_round",
      "pollster": "Odoxa",
      "commissioner": null,
      "publication_date": null,
      "fieldwork_start": "2026-03-25",
      "fieldwork_end": "2026-03-26",
      "sample_size": 1005,
      "matchup_key": "65030a6fcb5d4727884092ec44ff4f0a4d1375109b1cea022a76f117a403880b",
      "hypothesis": "Second round — Édouard Philippe vs Jordan Bardella",
      "candidates": [
        {
          "name": "Édouard Philippe",
          "score": 52
        },
        {
          "name": "Jordan Bardella",
          "score": 48
        }
      ],
      "margin": 4,
      "source_url": "https://www.odoxa.fr/sondage/spectaculaire-come-back-dedouard-philippe-il-remporterait-aujourdhui-la-presidentielle/",
      "source_page_url": "https://en.wikipedia.org/wiki/Opinion_polling_for_the_2027_French_presidential_election",
      "source_section": "Philippe vs. Bardella",
      "source_section_path": [
        "Second round",
        "Declined to be candidates",
        "Philippe vs. Bardella"
      ],
      "source_scope": "source_declined_candidate_section",
      "quality_flags": []
    },
    {
      "event_id": "0a128d1a04d4987eef7023fef8c544869788d018edf2a8c8fa9e3c78c4cdc941",
      "round": "second_round",
      "pollster": "Odoxa",
      "commissioner": null,
      "publication_date": null,
      "fieldwork_start": "2025-11-19",
      "fieldwork_end": "2025-11-20",
      "sample_size": 1300,
      "matchup_key": "65030a6fcb5d4727884092ec44ff4f0a4d1375109b1cea022a76f117a403880b",
      "hypothesis": "Second round — Édouard Philippe vs Jordan Bardella",
      "candidates": [
        {
          "name": "Édouard Philippe",
          "score": 47
        },
        {
          "name": "Jordan Bardella",
          "score": 53
        }
      ],
      "margin": 6,
      "source_url": "https://www.odoxa.fr/sondage/jordan-bardella-est-la-personnalite-politique-preferee-des-francais-et-remporterait-la-presidentielle-si-elle-avait-lieu-dimanche-prochain/",
      "source_page_url": "https://en.wikipedia.org/wiki/Opinion_polling_for_the_2027_French_presidential_election",
      "source_section": "Philippe vs. Bardella",
      "source_section_path": [
        "Second round",
        "Declined to be candidates",
        "Philippe vs. Bardella"
      ],
      "source_scope": "source_declined_candidate_section",
      "quality_flags": []
    },
    {
      "event_id": "fc7fa8547298e5e76d9157730548fbf2e260526eb386a56b0a9ad2e608ba9209",
      "round": "second_round",
      "pollster": "Odoxa",
      "commissioner": null,
      "publication_date": null,
      "fieldwork_start": "2025-11-19",
      "fieldwork_end": "2025-11-20",
      "sample_size": 1300,
      "matchup_key": "c8d3b8b02c325c5cf8da01e329f0eab1202473e2754696709fbbde861dce2b06",
      "hypothesis": "Second round — Jean-Luc Mélenchon vs Jordan Bardella",
      "candidates": [
        {
          "name": "Jean-Luc Mélenchon",
          "score": 26
        },
        {
          "name": "Jordan Bardella",
          "score": 74
        }
      ],
      "margin": 48,
      "source_url": "https://www.odoxa.fr/sondage/jordan-bardella-est-la-personnalite-politique-preferee-des-francais-et-remporterait-la-presidentielle-si-elle-avait-lieu-dimanche-prochain/",
      "source_page_url": "https://en.wikipedia.org/wiki/Opinion_polling_for_the_2027_French_presidential_election",
      "source_section": "Mélenchon vs. Bardella",
      "source_section_path": [
        "Second round",
        "Declined to be candidates",
        "Mélenchon vs. Bardella"
      ],
      "source_scope": "source_declined_candidate_section",
      "quality_flags": []
    },
    {
      "event_id": "75ed87a4a48d81558c42f89166562c80f26ca80c12126d20a5c3de591b1bea3f",
      "round": "second_round",
      "pollster": "Odoxa",
      "commissioner": null,
      "publication_date": null,
      "fieldwork_start": "2025-11-19",
      "fieldwork_end": "2025-11-20",
      "sample_size": 1300,
      "matchup_key": "e4174856272b72a0a855e88664f106fa90827e450b1692e3fdb78a0d2b03a683",
      "hypothesis": "Second round — Gabriel Attal vs Jordan Bardella",
      "candidates": [
        {
          "name": "Gabriel Attal",
          "score": 44
        },
        {
          "name": "Jordan Bardella",
          "score": 56
        }
      ],
      "margin": 12,
      "source_url": "https://www.odoxa.fr/sondage/presidentielle-le-pen-ou-bardella-seraient-en-tete-au-premier-tour-mais-battus-par-philippe-au-second/",
      "source_page_url": "https://en.wikipedia.org/wiki/Opinion_polling_for_the_2027_French_presidential_election",
      "source_section": "Attal vs. Bardella",
      "source_section_path": [
        "Second round",
        "Declined to be candidates",
        "Attal vs. Bardella"
      ],
      "source_scope": "source_declined_candidate_section",
      "quality_flags": []
    },
    {
      "event_id": "35d60d5654ce84831234eacb14e214eb40d29f7123249a96d0c9f5070d1acc92",
      "round": "second_round",
      "pollster": "Odoxa",
      "commissioner": null,
      "publication_date": null,
      "fieldwork_start": "2025-11-19",
      "fieldwork_end": "2025-11-20",
      "sample_size": 1300,
      "matchup_key": "f73fc321237dfe37284e53ff09259b95fd94d775515ac7edd64d296900e943ad",
      "hypothesis": "Second round — Raphaël Glucksmann vs Jordan Bardella",
      "candidates": [
        {
          "name": "Raphaël Glucksmann",
          "score": 42
        },
        {
          "name": "Jordan Bardella",
          "score": 58
        }
      ],
      "margin": 16,
      "source_url": "https://www.odoxa.fr/sondage/presidentielle-le-pen-ou-bardella-seraient-en-tete-au-premier-tour-mais-battus-par-philippe-au-second/",
      "source_page_url": "https://en.wikipedia.org/wiki/Opinion_polling_for_the_2027_French_presidential_election",
      "source_section": "Glucksmann vs. Bardella",
      "source_section_path": [
        "Second round",
        "Declined to be candidates",
        "Glucksmann vs. Bardella"
      ],
      "source_scope": "source_declined_candidate_section",
      "quality_flags": []
    },
    {
      "event_id": "b00cde1a8f06033ecd27f2f51c18e3a92a27cac82a0ba5f1bc0872e02e93acd9",
      "round": "second_round",
      "pollster": "Odoxa",
      "commissioner": null,
      "publication_date": null,
      "fieldwork_start": "2025-04-23",
      "fieldwork_end": "2025-04-24",
      "sample_size": 1005,
      "matchup_key": "65030a6fcb5d4727884092ec44ff4f0a4d1375109b1cea022a76f117a403880b",
      "hypothesis": "Second round — Édouard Philippe vs Jordan Bardella",
      "candidates": [
        {
          "name": "Édouard Philippe",
          "score": 54
        },
        {
          "name": "Jordan Bardella",
          "score": 46
        }
      ],
      "margin": 8,
      "source_url": "https://www.odoxa.fr/sondage/presidentielle-le-pen-ou-bardella-seraient-en-tete-au-premier-tour-mais-battus-par-philippe-au-second/",
      "source_page_url": "https://en.wikipedia.org/wiki/Opinion_polling_for_the_2027_French_presidential_election",
      "source_section": "Philippe vs. Bardella",
      "source_section_path": [
        "Second round",
        "Declined to be candidates",
        "Philippe vs. Bardella"
      ],
      "source_scope": "source_declined_candidate_section",
      "quality_flags": []
    },
    {
      "event_id": "c20a4a129956f78621b1594a31c719263efc847a259e57b0226b9128c27a5f78",
      "round": "second_round",
      "pollster": "Odoxa",
      "commissioner": null,
      "publication_date": null,
      "fieldwork_start": "2025-04-23",
      "fieldwork_end": "2025-04-24",
      "sample_size": 1005,
      "matchup_key": "783f1f9054fbd7487dab0b1689b7c3f1af200ebfec1ecf75d0078c6e65833198",
      "hypothesis": "Second round — Édouard Philippe vs Marine Le Pen",
      "candidates": [
        {
          "name": "Édouard Philippe",
          "score": 54
        },
        {
          "name": "Marine Le Pen",
          "score": 46
        }
      ],
      "margin": 8,
      "source_url": "https://www.odoxa.fr/sondage/presidentielle-le-pen-ou-bardella-seraient-en-tete-au-premier-tour-mais-battus-par-philippe-au-second/",
      "source_page_url": "https://en.wikipedia.org/wiki/Opinion_polling_for_the_2027_French_presidential_election",
      "source_section": "Philippe vs. Le Pen",
      "source_section_path": [
        "Second round",
        "Philippe vs. Le Pen"
      ],
      "source_scope": "current_tested",
      "quality_flags": []
    },
    {
      "event_id": "cfb9ecc41fc4fbc37065a249bb18b1f5be781096e7662bae869879326087221f",
      "round": "second_round",
      "pollster": "Ifop/Hexagone",
      "commissioner": null,
      "publication_date": null,
      "fieldwork_start": "2025-04-11",
      "fieldwork_end": "2025-04-18",
      "sample_size": 9128,
      "matchup_key": "65030a6fcb5d4727884092ec44ff4f0a4d1375109b1cea022a76f117a403880b",
      "hypothesis": "Second round — Édouard Philippe vs Jordan Bardella",
      "candidates": [
        {
          "name": "Édouard Philippe",
          "score": 50
        },
        {
          "name": "Jordan Bardella",
          "score": 50
        }
      ],
      "margin": 0,
      "source_url": "https://observatoire-hexagone.org/wp-content/uploads/2025/05/20250502_Hexagone_Grande-Enquete-Electorale-2025.pdf",
      "source_page_url": "https://en.wikipedia.org/wiki/Opinion_polling_for_the_2027_French_presidential_election",
      "source_section": "Philippe vs. Bardella",
      "source_section_path": [
        "Second round",
        "Declined to be candidates",
        "Philippe vs. Bardella"
      ],
      "source_scope": "source_declined_candidate_section",
      "quality_flags": []
    },
    {
      "event_id": "aa99294773918e4dc5adaffaba64d09f714516d7e4b579a7344a0ed4b97d468a",
      "round": "second_round",
      "pollster": "Ifop/Hexagone",
      "commissioner": null,
      "publication_date": null,
      "fieldwork_start": "2025-04-11",
      "fieldwork_end": "2025-04-18",
      "sample_size": 9128,
      "matchup_key": "783f1f9054fbd7487dab0b1689b7c3f1af200ebfec1ecf75d0078c6e65833198",
      "hypothesis": "Second round — Édouard Philippe vs Marine Le Pen",
      "candidates": [
        {
          "name": "Édouard Philippe",
          "score": 52
        },
        {
          "name": "Marine Le Pen",
          "score": 48
        }
      ],
      "margin": 4,
      "source_url": "https://observatoire-hexagone.org/wp-content/uploads/2025/05/20250502_Hexagone_Grande-Enquete-Electorale-2025.pdf",
      "source_page_url": "https://en.wikipedia.org/wiki/Opinion_polling_for_the_2027_French_presidential_election",
      "source_section": "Philippe vs. Le Pen",
      "source_section_path": [
        "Second round",
        "Philippe vs. Le Pen"
      ],
      "source_scope": "current_tested",
      "quality_flags": []
    },
    {
      "event_id": "b8473b739910f3b9b2a62cbf1c379188e3e8c9eb4fff92754a8419d4763514b1",
      "round": "second_round",
      "pollster": "Ifop/Hexagone",
      "commissioner": null,
      "publication_date": null,
      "fieldwork_start": "2025-04-11",
      "fieldwork_end": "2025-04-18",
      "sample_size": 9128,
      "matchup_key": "9fe645f9f24c1f7dc42b5a70cdc1b3fd829cbfeefcf3b38b82593419ad63daab",
      "hypothesis": "Second round — Bruno Retailleau vs Jordan Bardella",
      "candidates": [
        {
          "name": "Bruno Retailleau",
          "score": 47
        },
        {
          "name": "Jordan Bardella",
          "score": 53
        }
      ],
      "margin": 6,
      "source_url": "https://observatoire-hexagone.org/wp-content/uploads/2025/05/20250502_Hexagone_Grande-Enquete-Electorale-2025.pdf",
      "source_page_url": "https://en.wikipedia.org/wiki/Opinion_polling_for_the_2027_French_presidential_election",
      "source_section": "Retailleau vs. Bardella",
      "source_section_path": [
        "Second round",
        "Declined to be candidates",
        "Retailleau vs. Bardella"
      ],
      "source_scope": "source_declined_candidate_section",
      "quality_flags": []
    },
    {
      "event_id": "bae60c73fe365cadcc1cc4f6db5f2c0b3054d68f0ec6c90f4914994d6d25f5a2",
      "round": "second_round",
      "pollster": "Ifop/Hexagone",
      "commissioner": null,
      "publication_date": null,
      "fieldwork_start": "2025-04-11",
      "fieldwork_end": "2025-04-18",
      "sample_size": 9128,
      "matchup_key": "c8d3b8b02c325c5cf8da01e329f0eab1202473e2754696709fbbde861dce2b06",
      "hypothesis": "Second round — Jean-Luc Mélenchon vs Jordan Bardella",
      "candidates": [
        {
          "name": "Jean-Luc Mélenchon",
          "score": 33
        },
        {
          "name": "Jordan Bardella",
          "score": 67
        }
      ],
      "margin": 34,
      "source_url": "https://observatoire-hexagone.org/wp-content/uploads/2025/05/20250502_Hexagone_Grande-Enquete-Electorale-2025.pdf",
      "source_page_url": "https://en.wikipedia.org/wiki/Opinion_polling_for_the_2027_French_presidential_election",
      "source_section": "Mélenchon vs. Bardella",
      "source_section_path": [
        "Second round",
        "Declined to be candidates",
        "Mélenchon vs. Bardella"
      ],
      "source_scope": "source_declined_candidate_section",
      "quality_flags": []
    },
    {
      "event_id": "d479888da6e05531ab54707e992f04da151d82128c632fac33f257f057f63e6c",
      "round": "second_round",
      "pollster": "Ifop/Hexagone",
      "commissioner": null,
      "publication_date": null,
      "fieldwork_start": "2025-04-11",
      "fieldwork_end": "2025-04-18",
      "sample_size": 9128,
      "matchup_key": "e4174856272b72a0a855e88664f106fa90827e450b1692e3fdb78a0d2b03a683",
      "hypothesis": "Second round — Gabriel Attal vs Jordan Bardella",
      "candidates": [
        {
          "name": "Gabriel Attal",
          "score": 48
        },
        {
          "name": "Jordan Bardella",
          "score": 52
        }
      ],
      "margin": 4,
      "source_url": "https://observatoire-hexagone.org/wp-content/uploads/2025/05/20250502_Hexagone_Grande-Enquete-Electorale-2025.pdf",
      "source_page_url": "https://en.wikipedia.org/wiki/Opinion_polling_for_the_2027_French_presidential_election",
      "source_section": "Attal vs. Bardella",
      "source_section_path": [
        "Second round",
        "Declined to be candidates",
        "Attal vs. Bardella"
      ],
      "source_scope": "source_declined_candidate_section",
      "quality_flags": []
    },
    {
      "event_id": "8a0a724486175f59b655629d4292edcad32b31bf4ba3303e456626b9b5366615",
      "round": "second_round",
      "pollster": "Ifop",
      "commissioner": null,
      "publication_date": null,
      "fieldwork_start": "2024-04-20",
      "fieldwork_end": "2024-04-24",
      "sample_size": 1081,
      "matchup_key": "783f1f9054fbd7487dab0b1689b7c3f1af200ebfec1ecf75d0078c6e65833198",
      "hypothesis": "Second round — Édouard Philippe vs Marine Le Pen",
      "candidates": [
        {
          "name": "Édouard Philippe",
          "score": 49
        },
        {
          "name": "Marine Le Pen",
          "score": 51
        }
      ],
      "margin": 2,
      "source_url": "https://www.ifop.com/wp-content/uploads/2024/04/120799-Resultats-ensemble.pdf",
      "source_page_url": "https://en.wikipedia.org/wiki/Opinion_polling_for_the_2027_French_presidential_election",
      "source_section": "Philippe vs. Le Pen",
      "source_section_path": [
        "Second round",
        "Philippe vs. Le Pen"
      ],
      "source_scope": "current_tested",
      "quality_flags": []
    },
    {
      "event_id": "c2a105f92db86374ca6d8e54177d5dcabb42c4c66c67a24aead5fb66797cacc0",
      "round": "second_round",
      "pollster": "Ifop",
      "commissioner": null,
      "publication_date": null,
      "fieldwork_start": "2024-04-20",
      "fieldwork_end": "2024-04-24",
      "sample_size": 1081,
      "matchup_key": "b02eec6f80ed4da2173d14e7ed6b2aa3877cf725f91d41f2c8850c66af2640ed",
      "hypothesis": "Second round — Gabriel Attal vs Marine Le Pen",
      "candidates": [
        {
          "name": "Gabriel Attal",
          "score": 47
        },
        {
          "name": "Marine Le Pen",
          "score": 53
        }
      ],
      "margin": 6,
      "source_url": "https://www.ifop.com/wp-content/uploads/2024/04/120799-Resultats-ensemble.pdf",
      "source_page_url": "https://en.wikipedia.org/wiki/Opinion_polling_for_the_2027_French_presidential_election",
      "source_section": "Attal vs. Le Pen",
      "source_section_path": [
        "Second round",
        "Attal vs. Le Pen"
      ],
      "source_scope": "current_tested",
      "quality_flags": []
    },
    {
      "event_id": "5872aaa20fe9861dcac1b551d1a990e77be716da1eac092c3b2f2cd32d036c98",
      "round": "second_round",
      "pollster": "Cluster17",
      "commissioner": null,
      "publication_date": null,
      "fieldwork_start": "2024-04-02",
      "fieldwork_end": "2024-04-05",
      "sample_size": 1686,
      "matchup_key": "2b8ffef90d7e509dde822706d04e47374f6afb95cbdddc43ba28aa7f81497cfc",
      "hypothesis": "Second round — Jean-Luc Mélenchon vs Marine Le Pen",
      "candidates": [
        {
          "name": "Jean-Luc Mélenchon",
          "score": 35
        },
        {
          "name": "Marine Le Pen",
          "score": 65
        }
      ],
      "margin": 30,
      "source_url": "http://www.commission-des-sondages.fr/notices/files/notices/2024/avril/9753-pdt-ruffin-cluster-17-picardie-debout-21-avril-2024.pdf",
      "source_page_url": "https://en.wikipedia.org/wiki/Opinion_polling_for_the_2027_French_presidential_election",
      "source_section": "Mélenchon vs. Le Pen",
      "source_section_path": [
        "Second round",
        "Mélenchon vs. Le Pen"
      ],
      "source_scope": "current_tested",
      "quality_flags": []
    },
    {
      "event_id": "a1e857f2bfd0aafcc768e05eea451a65b7122c7231b01a35d225accafa58f934",
      "round": "second_round",
      "pollster": "Cluster17",
      "commissioner": null,
      "publication_date": null,
      "fieldwork_start": "2024-04-02",
      "fieldwork_end": "2024-04-05",
      "sample_size": 1686,
      "matchup_key": "78ee22bdc7b20f010e4240afc3268ceb9f2bdb50e8a49b6be5fccd3c5f8e77f9",
      "hypothesis": "Second round — François Ruffin vs Marine Le Pen",
      "candidates": [
        {
          "name": "François Ruffin",
          "score": 50
        },
        {
          "name": "Marine Le Pen",
          "score": 50
        }
      ],
      "margin": 0,
      "source_url": "http://www.commission-des-sondages.fr/notices/files/notices/2024/avril/9753-pdt-ruffin-cluster-17-picardie-debout-21-avril-2024.pdf",
      "source_page_url": "https://en.wikipedia.org/wiki/Opinion_polling_for_the_2027_French_presidential_election",
      "source_section": "Ruffin vs. Le Pen",
      "source_section_path": [
        "Second round",
        "Ruffin vs. Le Pen"
      ],
      "source_scope": "current_tested",
      "quality_flags": []
    },
    {
      "event_id": "ad7ec560a0b8762e3008390fcb992bde6c9e7a080a8ffd3c5f1dc1cd22ccb149",
      "round": "second_round",
      "pollster": "Ifop",
      "commissioner": null,
      "publication_date": null,
      "fieldwork_start": "2024-01-31",
      "fieldwork_end": "2024-02-01",
      "sample_size": 1081,
      "matchup_key": "2b8ffef90d7e509dde822706d04e47374f6afb95cbdddc43ba28aa7f81497cfc",
      "hypothesis": "Second round — Jean-Luc Mélenchon vs Marine Le Pen",
      "candidates": [
        {
          "name": "Jean-Luc Mélenchon",
          "score": 36
        },
        {
          "name": "Marine Le Pen",
          "score": 64
        }
      ],
      "margin": 28,
      "source_url": "https://www.ifop.com/wp-content/uploads/2024/02/120604-Resultats.pdf",
      "source_page_url": "https://en.wikipedia.org/wiki/Opinion_polling_for_the_2027_French_presidential_election",
      "source_section": "Mélenchon vs. Le Pen",
      "source_section_path": [
        "Second round",
        "Mélenchon vs. Le Pen"
      ],
      "source_scope": "current_tested",
      "quality_flags": []
    },
    {
      "event_id": "da45785b3bb1bbab937e68bedd87e83d16d693971354bf517f2b55732abb2e63",
      "round": "second_round",
      "pollster": "Ifop",
      "commissioner": null,
      "publication_date": null,
      "fieldwork_start": "2024-01-31",
      "fieldwork_end": "2024-02-01",
      "sample_size": 1081,
      "matchup_key": "783f1f9054fbd7487dab0b1689b7c3f1af200ebfec1ecf75d0078c6e65833198",
      "hypothesis": "Second round — Édouard Philippe vs Marine Le Pen",
      "candidates": [
        {
          "name": "Édouard Philippe",
          "score": 50
        },
        {
          "name": "Marine Le Pen",
          "score": 50
        }
      ],
      "margin": 0,
      "source_url": "https://www.ifop.com/wp-content/uploads/2024/02/120604-Resultats.pdf",
      "source_page_url": "https://en.wikipedia.org/wiki/Opinion_polling_for_the_2027_French_presidential_election",
      "source_section": "Philippe vs. Le Pen",
      "source_section_path": [
        "Second round",
        "Philippe vs. Le Pen"
      ],
      "source_scope": "current_tested",
      "quality_flags": []
    },
    {
      "event_id": "12fd968681ec8151f82e077fc267c2a3c2fc84aa74c548bed811ef5be86e4c66",
      "round": "second_round",
      "pollster": "Ifop",
      "commissioner": null,
      "publication_date": null,
      "fieldwork_start": "2024-01-31",
      "fieldwork_end": "2024-02-01",
      "sample_size": 1081,
      "matchup_key": "b02eec6f80ed4da2173d14e7ed6b2aa3877cf725f91d41f2c8850c66af2640ed",
      "hypothesis": "Second round — Gabriel Attal vs Marine Le Pen",
      "candidates": [
        {
          "name": "Gabriel Attal",
          "score": 49
        },
        {
          "name": "Marine Le Pen",
          "score": 51
        }
      ],
      "margin": 2,
      "source_url": "https://www.ifop.com/wp-content/uploads/2024/02/120604-Resultats.pdf",
      "source_page_url": "https://en.wikipedia.org/wiki/Opinion_polling_for_the_2027_French_presidential_election",
      "source_section": "Attal vs. Le Pen",
      "source_section_path": [
        "Second round",
        "Attal vs. Le Pen"
      ],
      "source_scope": "current_tested",
      "quality_flags": []
    }
  ]
}
